KeyisBClient_mmbp/Client.py
KeyisBClient_mmbp/__init__.py
KeyisBClient_mmbp/gw_certs/__init__.py
KeyisBClient_mmbp/gw_certs/v0.0.1.crt
keyisbclient_mmbp-0.0.0.1.22.dist-info/licenses/LICENSE
keyisbclient_mmbp-0.0.0.1.22.dist-info/METADATA
keyisbclient_mmbp-0.0.0.1.22.dist-info/WHEEL
keyisbclient_mmbp-0.0.0.1.22.dist-info/top_level.txt
keyisbclient_mmbp-0.0.0.1.22.dist-info/RECORD
