Metadata-Version: 2.4
Name: KeyisBClient_mmbp
Version: 0.0.0.1.22
Summary: KeyisBClient_mmbp
Home-page: https://github.com/KeyisB/libs/tree/main/KeyisBClient_mmbp
Author: KeyisB
Author-email: keyisb.pip@gmail.com
License: MMB License v1.0
Classifier: Programming Language :: Python :: 3
Classifier: Operating System :: OS Independent
Requires-Python: >=3.12
License-File: LICENSE
Requires-Dist: KeyisBClient
Requires-Dist: httpx
Dynamic: author
Dynamic: author-email
Dynamic: classifier
Dynamic: description
Dynamic: description-content-type
Dynamic: home-page
Dynamic: license
Dynamic: license-file
Dynamic: requires-dist
Dynamic: requires-python
Dynamic: summary
